exam5/ex1 copy/a.v

module comp2(A,M);
    input [7:0] A;
    output [7:0] M;

    assign M = ~A+1;
endmodule

module comp2_test;
    reg [7:0] A;
    wire [7:0] M;
    integer i;

    comp2 c (A,M);

    initial begin;
        $dumpfile("comp_2.vcd");
        $dumpvars(0);
        $monitor("%4t A:%b M:%b", $time, A, M);


        for(i=-63; i<65; i=i+1)
        begin
             #1 A=i;

        end

        #1 $finish;
    end                // シミュレーションの終了指示

endmodule

exam5/ex1 copy/comp_2.vcd
$date
	Sun Jun 14 16:41:41 2020
$end
$version
	Icarus Verilog
$end
$timescale
	1s
$end
$scope module comp2_test $end
$var wire 8 ! M [7:0] $end
$var reg 8 " A [7:0] $end
$var integer 32 # i [31:0] $end
$scope module c $end
$var wire 8 $ A [7:0] $end
$var wire 8 % M [7:0] $end
$upscope $end
$upscope $end
$enddefinitions $end
#0
$dumpvars
bx %
bx $
b11111111111111111111111111000001 #
bx "
bx !
$end
#1
b111111 !
b111111 %
b11111111111111111111111111000010 #
b11000001 "
b11000001 $
#2
b111110 !
b111110 %
b11111111111111111111111111000011 #
b11000010 "
b11000010 $
#3
b111101 !
b111101 %
b11111111111111111111111111000100 #
b11000011 "
b11000011 $
#4
b111100 !
b111100 %
b11111111111111111111111111000101 #
b11000100 "
b11000100 $
#5
b111011 !
b111011 %
b11111111111111111111111111000110 #
b11000101 "
b11000101 $
#6
b111010 !
b111010 %
b11111111111111111111111111000111 #
b11000110 "
b11000110 $
#7
b111001 !
b111001 %
b11111111111111111111111111001000 #
b11000111 "
b11000111 $
#8
b111000 !
b111000 %
b11111111111111111111111111001001 #
b11001000 "
b11001000 $
#9
b110111 !
b110111 %
b11111111111111111111111111001010 #
b11001001 "
b11001001 $
#10
b110110 !
b110110 %
b11111111111111111111111111001011 #
b11001010 "
b11001010 $
#11
b110101 !
b110101 %
b11111111111111111111111111001100 #
b11001011 "
b11001011 $
#12
b110100 !
b110100 %
b11111111111111111111111111001101 #
b11001100 "
b11001100 $
#13
b110011 !
b110011 %
b11111111111111111111111111001110 #
b11001101 "
b11001101 $
#14
b110010 !
b110010 %
b11111111111111111111111111001111 #
b11001110 "
b11001110 $
#15
b110001 !
b110001 %
b11111111111111111111111111010000 #
b11001111 "
b11001111 $
#16
b110000 !
b110000 %
b11111111111111111111111111010001 #
b11010000 "
b11010000 $
#17
b101111 !
b101111 %
b11111111111111111111111111010010 #
b11010001 "
b11010001 $
#18
b101110 !
b101110 %
b11111111111111111111111111010011 #
b11010010 "
b11010010 $
#19
b101101 !
b101101 %
b11111111111111111111111111010100 #
b11010011 "
b11010011 $
#20
b101100 !
b101100 %
b11111111111111111111111111010101 #
b11010100 "
b11010100 $
#21
b101011 !
b101011 %
b11111111111111111111111111010110 #
b11010101 "
b11010101 $
#22
b101010 !
b101010 %
b11111111111111111111111111010111 #
b11010110 "
b11010110 $
#23
b101001 !
b101001 %
b11111111111111111111111111011000 #
b11010111 "
b11010111 $
#24
b101000 !
b101000 %
b11111111111111111111111111011001 #
b11011000 "
b11011000 $
#25
b100111 !
b100111 %
b11111111111111111111111111011010 #
b11011001 "
b11011001 $
#26
b100110 !
b100110 %
b11111111111111111111111111011011 #
b11011010 "
b11011010 $
#27
b100101 !
b100101 %
b11111111111111111111111111011100 #
b11011011 "
b11011011 $
#28
b100100 !
b100100 %
b11111111111111111111111111011101 #
b11011100 "
b11011100 $
#29
b100011 !
b100011 %
b11111111111111111111111111011110 #
b11011101 "
b11011101 $
#30
b100010 !
b100010 %
b11111111111111111111111111011111 #
b11011110 "
b11011110 $
#31
b100001 !
b100001 %
b11111111111111111111111111100000 #
b11011111 "
b11011111 $
#32
b100000 !
b100000 %
b11111111111111111111111111100001 #
b11100000 "
b11100000 $
#33
b11111 !
b11111 %
b11111111111111111111111111100010 #
b11100001 "
b11100001 $
#34
b11110 !
b11110 %
b11111111111111111111111111100011 #
b11100010 "
b11100010 $
#35
b11101 !
b11101 %
b11111111111111111111111111100100 #
b11100011 "
b11100011 $
#36
b11100 !
b11100 %
b11111111111111111111111111100101 #
b11100100 "
b11100100 $
#37
b11011 !
b11011 %
b11111111111111111111111111100110 #
b11100101 "
b11100101 $
#38
b11010 !
b11010 %
b11111111111111111111111111100111 #
b11100110 "
b11100110 $
#39
b11001 !
b11001 %
b11111111111111111111111111101000 #
b11100111 "
b11100111 $
#40
b11000 !
b11000 %
b11111111111111111111111111101001 #
b11101000 "
b11101000 $
#41
b10111 !
b10111 %
b11111111111111111111111111101010 #
b11101001 "
b11101001 $
#42
b10110 !
b10110 %
b11111111111111111111111111101011 #
b11101010 "
b11101010 $
#43
b10101 !
b10101 %
b11111111111111111111111111101100 #
b11101011 "
b11101011 $
#44
b10100 !
b10100 %
b11111111111111111111111111101101 #
b11101100 "
b11101100 $
#45
b10011 !
b10011 %
b11111111111111111111111111101110 #
b11101101 "
b11101101 $
#46
b10010 !
b10010 %
b11111111111111111111111111101111 #
b11101110 "
b11101110 $
#47
b10001 !
b10001 %
b11111111111111111111111111110000 #
b11101111 "
b11101111 $
#48
b10000 !
b10000 %
b11111111111111111111111111110001 #
b11110000 "
b11110000 $
#49
b1111 !
b1111 %
b11111111111111111111111111110010 #
b11110001 "
b11110001 $
#50
b1110 !
b1110 %
b11111111111111111111111111110011 #
b11110010 "
b11110010 $
#51
b1101 !
b1101 %
b11111111111111111111111111110100 #
b11110011 "
b11110011 $
#52
b1100 !
b1100 %
b11111111111111111111111111110101 #
b11110100 "
b11110100 $
#53
b1011 !
b1011 %
b11111111111111111111111111110110 #
b11110101 "
b11110101 $
#54
b1010 !
b1010 %
b11111111111111111111111111110111 #
b11110110 "
b11110110 $
#55
b1001 !
b1001 %
b11111111111111111111111111111000 #
b11110111 "
b11110111 $
#56
b1000 !
b1000 %
b11111111111111111111111111111001 #
b11111000 "
b11111000 $
#57
b111 !
b111 %
b11111111111111111111111111111010 #
b11111001 "
b11111001 $
#58
b110 !
b110 %
b11111111111111111111111111111011 #
b11111010 "
b11111010 $
#59
b101 !
b101 %
b11111111111111111111111111111100 #
b11111011 "
b11111011 $
#60
b100 !
b100 %
b11111111111111111111111111111101 #
b11111100 "
b11111100 $
#61
b11 !
b11 %
b11111111111111111111111111111110 #
b11111101 "
b11111101 $
#62
b10 !
b10 %
b11111111111111111111111111111111 #
b11111110 "
b11111110 $
#63
b1 !
b1 %
b0 #
b11111111 "
b11111111 $
#64
b0 !
b0 %
b1 #
b0 "
b0 $
#65
b11111111 !
b11111111 %
b10 #
b1 "
b1 $
#66
b11111110 !
b11111110 %
b11 #
b10 "
b10 $
#67
b11111101 !
b11111101 %
b100 #
b11 "
b11 $
#68
b11111100 !
b11111100 %
b101 #
b100 "
b100 $
#69
b11111011 !
b11111011 %
b110 #
b101 "
b101 $
#70
b11111010 !
b11111010 %
b111 #
b110 "
b110 $
#71
b11111001 !
b11111001 %
b1000 #
b111 "
b111 $
#72
b11111000 !
b11111000 %
b1001 #
b1000 "
b1000 $
#73
b11110111 !
b11110111 %
b1010 #
b1001 "
b1001 $
#74
b11110110 !
b11110110 %
b1011 #
b1010 "
b1010 $
#75
b11110101 !
b11110101 %
b1100 #
b1011 "
b1011 $
#76
b11110100 !
b11110100 %
b1101 #
b1100 "
b1100 $
#77
b11110011 !
b11110011 %
b1110 #
b1101 "
b1101 $
#78
b11110010 !
b11110010 %
b1111 #
b1110 "
b1110 $
#79
b11110001 !
b11110001 %
b10000 #
b1111 "
b1111 $
#80
b11110000 !
b11110000 %
b10001 #
b10000 "
b10000 $
#81
b11101111 !
b11101111 %
b10010 #
b10001 "
b10001 $
#82
b11101110 !
b11101110 %
b10011 #
b10010 "
b10010 $
#83
b11101101 !
b11101101 %
b10100 #
b10011 "
b10011 $
#84
b11101100 !
b11101100 %
b10101 #
b10100 "
b10100 $
#85
b11101011 !
b11101011 %
b10110 #
b10101 "
b10101 $
#86
b11101010 !
b11101010 %
b10111 #
b10110 "
b10110 $
#87
b11101001 !
b11101001 %
b11000 #
b10111 "
b10111 $
#88
b11101000 !
b11101000 %
b11001 #
b11000 "
b11000 $
#89
b11100111 !
b11100111 %
b11010 #
b11001 "
b11001 $
#90
b11100110 !
b11100110 %
b11011 #
b11010 "
b11010 $
#91
b11100101 !
b11100101 %
b11100 #
b11011 "
b11011 $
#92
b11100100 !
b11100100 %
b11101 #
b11100 "
b11100 $
#93
b11100011 !
b11100011 %
b11110 #
b11101 "
b11101 $
#94
b11100010 !
b11100010 %
b11111 #
b11110 "
b11110 $
#95
b11100001 !
b11100001 %
b100000 #
b11111 "
b11111 $
#96
b11100000 !
b11100000 %
b100001 #
b100000 "
b100000 $
#97
b11011111 !
b11011111 %
b100010 #
b100001 "
b100001 $
#98
b11011110 !
b11011110 %
b100011 #
b100010 "
b100010 $
#99
b11011101 !
b11011101 %
b100100 #
b100011 "
b100011 $
#100
b11011100 !
b11011100 %
b100101 #
b100100 "
b100100 $
#101
b11011011 !
b11011011 %
b100110 #
b100101 "
b100101 $
#102
b11011010 !
b11011010 %
b100111 #
b100110 "
b100110 $
#103
b11011001 !
b11011001 %
b101000 #
b100111 "
b100111 $
#104
b11011000 !
b11011000 %
b101001 #
b101000 "
b101000 $
#105
b11010111 !
b11010111 %
b101010 #
b101001 "
b101001 $
#106
b11010110 !
b11010110 %
b101011 #
b101010 "
b101010 $
#107
b11010101 !
b11010101 %
b101100 #
b101011 "
b101011 $
#108
b11010100 !
b11010100 %
b101101 #
b101100 "
b101100 $
#109
b11010011 !
b11010011 %
b101110 #
b101101 "
b101101 $
#110
b11010010 !
b11010010 %
b101111 #
b101110 "
b101110 $
#111
b11010001 !
b11010001 %
b110000 #
b101111 "
b101111 $
#112
b11010000 !
b11010000 %
b110001 #
b110000 "
b110000 $
#113
b11001111 !
b11001111 %
b110010 #
b110001 "
b110001 $
#114
b11001110 !
b11001110 %
b110011 #
b110010 "
b110010 $
#115
b11001101 !
b11001101 %
b110100 #
b110011 "
b110011 $
#116
b11001100 !
b11001100 %
b110101 #
b110100 "
b110100 $
#117
b11001011 !
b11001011 %
b110110 #
b110101 "
b110101 $
#118
b11001010 !
b11001010 %
b110111 #
b110110 "
b110110 $
#119
b11001001 !
b11001001 %
b111000 #
b110111 "
b110111 $
#120
b11001000 !
b11001000 %
b111001 #
b111000 "
b111000 $
#121
b11000111 !
b11000111 %
b111010 #
b111001 "
b111001 $
#122
b11000110 !
b11000110 %
b111011 #
b111010 "
b111010 $
#123
b11000101 !
b11000101 %
b111100 #
b111011 "
b111011 $
#124
b11000100 !
b11000100 %
b111101 #
b111100 "
b111100 $
#125
b11000011 !
b11000011 %
b111110 #
b111101 "
b111101 $
#126
b11000010 !
b11000010 %
b111111 #
b111110 "
b111110 $
#127
b11000001 !
b11000001 %
b1000000 #
b111111 "
b111111 $
#128
b11000000 !
b11000000 %
b1000001 #
b1000000 "
b1000000 $
