exam2/ex4/e4.v
module FA (a,b,ci,s,co);
  input a,b,ci;
  output s,co;
  assign s = a^b^ci;
  assign co = a&b|b&ci|ci&a;
endmodule

`timescale 1 ns / 1 ns

module FA_TEST;
  reg a,b,ci;
  wire s,co;

  FA A(a,b,ci,s,co);
  initial begin
    $dumpfile("FA_TEST.vcd");
    $dumpvars(0);
    $monitor("%4t a:%b b:%b ci:%b co:%b s:%b ",$time, a,b,ci,co,s);

    a = 0;
    b = 0;
    ci = 0;

    #10 a = 1;
    #10 b = 1;
    #10 a = 0;
    #10 b = 0;
    #0 ci = 1;
    #10 a = 1;
    #10 b = 1;
    #10 a = 0;
    #10 $finish;
  end
endmodule

exam2/ex4/FA_TEST.vcd
$date
	Mon May 18 10:36:57 2020
$end
$version
	Icarus Verilog
$end
$timescale
	1ns
$end
$scope module FA_TEST $end
$var wire 1 ! s $end
$var wire 1 " co $end
$var reg 1 # a $end
$var reg 1 $ b $end
$var reg 1 % ci $end
$scope module A $end
$var wire 1 # a $end
$var wire 1 $ b $end
$var wire 1 % ci $end
$var wire 1 " co $end
$var wire 1 ! s $end
$upscope $end
$upscope $end
$enddefinitions $end
#0
$dumpvars
0%
0$
0#
0"
0!
$end
#10
1!
1#
#20
1"
0!
1$
#30
0"
1!
0#
#40
1%
0$
#50
0!
1"
1#
#60
1!
1$
#70
0!
0#
