exam4/3a/a.v
module PENC4(A, Y, VALID);
 // A：4 bit 入力，Y：2 bit エンコード出力，VALID：有効信号（= 1：Y 出力有効）
    input [3:0] A;
    output [1:0] Y;
    output VALID;

    function [2:0] enc;
        input [7:0] a;
        if      (A&4'b1000) enc = 3;
        else if (A&4'b0100) enc = 2;
        else if (A&4'b0010) enc = 1;
        else if (A&4'b0001) enc = 0;
        else enc = 0;
    endfunction

    assign Y = enc(A);
    assign VALID = |A;
endmodule

module PENC4_TEST;
    reg [3:0] A;
    wire [1:0] Y;
    wire V;

    integer i;

    PENC4 P (A, Y, V);

    initial begin;
        $dumpfile("pe4.vcd");    // CKTKWave による波形表示のためのシミュレーション結果出力ファイル名指定
        $dumpvars(0);        // すべての信号を表示対象とするための設定
        $monitor("%4t A:%d Y:%d Valid:%d", $time, A, Y, V);    // 表示設定

        A=0;
        for(i=1;i<16;i=i+1) begin
            #10 A=i;
        end
        #10 $finish;
    end
endmodule

exam4/3a/pe4.vcd
$date
	Tue Jun  2 22:40:22 2020
$end
$version
	Icarus Verilog
$end
$timescale
	1s
$end
$scope module PENC4_TEST $end
$var wire 2 ! Y [1:0] $end
$var wire 1 " V $end
$var reg 4 # A [3:0] $end
$var integer 32 $ i [31:0] $end
$scope module P $end
$var wire 4 % A [3:0] $end
$var wire 2 & Y [1:0] $end
$var wire 1 " VALID $end
$scope function enc $end
$var reg 8 ' a [7:0] $end
$var reg 3 ( enc [2:0] $end
$upscope $end
$upscope $end
$upscope $end
$enddefinitions $end
#0
$dumpvars
b0 (
b0 '
b0 &
b0 %
b1 $
b0 #
0"
b0 !
$end
#10
b1 '
b10 $
1"
b1 #
b1 %
#20
b1 !
b1 &
b1 (
b10 '
b11 $
b10 #
b10 %
#30
b11 '
b100 $
b11 #
b11 %
#40
b10 !
b10 &
b10 (
b100 '
b101 $
b100 #
b100 %
#50
b101 '
b110 $
b101 #
b101 %
#60
b110 '
b111 $
b110 #
b110 %
#70
b111 '
b1000 $
b111 #
b111 %
#80
b11 !
b11 &
b11 (
b1000 '
b1001 $
b1000 #
b1000 %
#90
b1001 '
b1010 $
b1001 #
b1001 %
#100
b1010 '
b1011 $
b1010 #
b1010 %
#110
b1011 '
b1100 $
b1011 #
b1011 %
#120
b1100 '
b1101 $
b1100 #
b1100 %
#130
b1101 '
b1110 $
b1101 #
b1101 %
#140
b1110 '
b1111 $
b1110 #
b1110 %
#150
b1111 '
b10000 $
b1111 #
b1111 %
