miyake/ex6/3d/a.v
`timescale 1 ns / 1 ns

module BCD_COUNT_A(CK, CE, AR, CO, Q); // CE = 1 で CK = 0 から CK = 1 に立ち上がるとカウントアップ
    input CK, CE, AR;
    output CO;
    reg CO;
    output [3:0] Q;
    reg [3:0] Q;

    always @ (posedge CK or negedge AR)
    begin
        if(~AR | Q[3]&Q[0]&CE)
            Q = 0;
        else if(CE)
            Q = Q+1;

        CO = Q[3]&Q[0]&CE;
    end
endmodule

module BCD2_COUNT_A(CK, CE, AR, CO, Q); // Q：8 bit（BCD 4 bit x 2 桁分），他は 3c) と同様
    input CK, CE, AR;
    output CO;
    output [7:0] Q;

    wire [3:0] upper, lower;
    wire co1, co2;

    BCD_COUNT BC1(CK, CE, AR, co1, lower);
    BCD_COUNT BC2(~co1, CE, AR, co2, upper);

    assign Q[7:4] = upper;
    assign Q[3:0] = lower;
    assign CO = Q[7]&Q[4]&Q[3]&Q[0];
endmodule

module BCD_COUNT(CK, CE, AR, CO, Q);
  input CK, CE, AR;
  output CO;
  reg CO = 0;
  output [3:0]Q;
  reg [3:0]Q;
  always @(posedge CK&CE or negedge AR)
  begin
    if (~AR)
      begin
      assign Q = 0;
      CO = 0;
      end
    else if (CO)
      begin
      assign Q = 0;
      CO = 0;
      end
    else
      begin
      assign Q = Q + 1;
      if (Q == 4'b1001)
        begin
        CO = 1;
        end
      end
  end
endmodule

module BCD2_COUNT(CK, CE, AR, CO, Q);
  input CK, CE, AR;
  output CO;
  output [7:0]Q;
  wire [3:0]q1;
  wire [3:0]q2;
  wire co1, co2;
  BCD_COUNT BCD1 (CK, CE, AR, co1, q1);
  BCD_COUNT BCD2 (~co1, CE, AR, co2, q2);
  assign Q = {q2, q1};
  assign CO = co1 & co2;
endmodule

module bcd2_test;
    reg CK ,CE, AR;
    wire CO, COA;
    wire [7:0] Q, QA;

    BCD2_COUNT bc2 (CK, CE, AR, CO, Q);
    BCD2_COUNT_A bc2a (CK, CE, AR, COA, QA);

    initial begin;
        $dumpfile("test.vcd");
        $dumpvars(0);
        $monitor("%4t CK:%b CE:%b AR:%b CO:%b COA:%b Q:%b QA:%b",$time, CK, CE, AR, CO, COA, Q, QA);

        CK = 0;
        CE = 0;
        AR = 1;
        #1 AR = 0;
        #1 AR = 1;
        CE = 1;
        #8 AR = 0;
        #1 AR = 1;
        //#1 AR = 0;
        /*
        #4 AR = 1;
           CE = 1;
        #20 CE = 0;
        #20 CE = 1;
        #155 CE = 0;
        #20 CE = 1;
        #39 AR = 0;
        #1 AR = 1;
        #20 $finish;
        */
        #500 $finish;
    end

    always #2
        CK <= ~CK;
endmodule

miyake/ex6/3d/test.vcd
$date
	Sun Jun 28 01:16:37 2020
$end
$version
	Icarus Verilog
$end
$timescale
	1ns
$end
$scope module BCD_COUNT_A $end
$var wire 1 ! AR $end
$var wire 1 " CE $end
$var wire 1 # CK $end
$var reg 1 $ CO $end
$var reg 4 % Q [3:0] $end
$upscope $end
$scope module bcd2_test $end
$var wire 8 & QA [7:0] $end
$var wire 8 ' Q [7:0] $end
$var wire 1 ( COA $end
$var wire 1 ) CO $end
$var reg 1 * AR $end
$var reg 1 + CE $end
$var reg 1 , CK $end
$scope module bc2 $end
$var wire 1 * AR $end
$var wire 1 + CE $end
$var wire 1 , CK $end
$var wire 1 ) CO $end
$var wire 4 - q2 [3:0] $end
$var wire 4 . q1 [3:0] $end
$var wire 1 / co2 $end
$var wire 1 0 co1 $end
$var wire 8 1 Q [7:0] $end
$scope module BCD1 $end
$var wire 1 * AR $end
$var wire 1 + CE $end
$var wire 1 , CK $end
$var reg 1 0 CO $end
$var reg 4 2 Q [3:0] $end
$upscope $end
$scope module BCD2 $end
$var wire 1 * AR $end
$var wire 1 + CE $end
$var wire 1 3 CK $end
$var reg 1 / CO $end
$var reg 4 4 Q [3:0] $end
$upscope $end
$upscope $end
$scope module bc2a $end
$var wire 1 * AR $end
$var wire 1 + CE $end
$var wire 1 , CK $end
$var wire 1 ( CO $end
$var wire 4 5 upper [3:0] $end
$var wire 4 6 lower [3:0] $end
$var wire 1 7 co2 $end
$var wire 1 8 co1 $end
$var wire 8 9 Q [7:0] $end
$scope module BC1 $end
$var wire 1 * AR $end
$var wire 1 + CE $end
$var wire 1 , CK $end
$var reg 1 8 CO $end
$var reg 4 : Q [3:0] $end
$upscope $end
$scope module BC2 $end
$var wire 1 * AR $end
$var wire 1 + CE $end
$var wire 1 ; CK $end
$var reg 1 7 CO $end
$var reg 4 < Q [3:0] $end
$upscope $end
$upscope $end
$upscope $end
$enddefinitions $end
#0
$dumpvars
bx <
1;
bx :
bx 9
08
07
bx 6
bx 5
bx 4
13
bx 2
bx 1
00
0/
bx .
bx -
0,
0+
1*
0)
x(
bx '
bx &
bx %
x$
z#
z"
z!
$end
#1
0(
b0 .
b0 2
b0 '
b0 1
b0 -
b0 4
b0 6
b0 :
b0 &
b0 9
b0 5
b0 <
0*
#2
b1 .
b1 2
b1 6
b1 :
1,
b10001 '
b10001 1
b1 -
b1 4
b10001 &
b10001 9
b1 5
b1 <
1+
1*
#4
0,
#6
b10010 '
b10010 1
b10 .
b10 2
b10010 &
b10010 9
b10 6
b10 :
1,
#8
0,
#10
1,
b0 .
b0 2
b0 '
b0 1
b0 -
b0 4
b0 6
b0 :
b0 &
b0 9
b0 5
b0 <
0*
#11
1*
#12
0,
#14
b1 '
b1 1
b1 .
b1 2
b1 &
b1 9
b1 6
b1 :
1,
#16
0,
#18
b10 '
b10 1
b10 .
b10 2
b10 &
b10 9
b10 6
b10 :
1,
#20
0,
#22
b11 '
b11 1
b11 .
b11 2
b11 &
b11 9
b11 6
b11 :
1,
#24
0,
#26
b100 '
b100 1
b100 .
b100 2
b100 &
b100 9
b100 6
b100 :
1,
#28
0,
#30
b101 '
b101 1
b101 .
b101 2
b101 &
b101 9
b101 6
b101 :
1,
#32
0,
#34
b110 '
b110 1
b110 .
b110 2
b110 &
b110 9
b110 6
b110 :
1,
#36
0,
#38
b111 '
b111 1
b111 .
b111 2
b111 &
b111 9
b111 6
b111 :
1,
#40
0,
#42
b1000 '
b1000 1
b1000 .
b1000 2
b1000 &
b1000 9
b1000 6
b1000 :
1,
#44
0,
#46
03
0;
10
b1001 '
b1001 1
b1001 .
b1001 2
18
b1001 &
b1001 9
b1001 6
b1001 :
1,
#48
0,
#50
b1 -
b1 4
b1 5
b1 <
13
1;
00
b10000 '
b10000 1
b0 .
b0 2
08
b10000 &
b10000 9
b0 6
b0 :
1,
#52
0,
#54
b10001 '
b10001 1
b1 .
b1 2
b10001 &
b10001 9
b1 6
b1 :
1,
#56
0,
#58
b10010 '
b10010 1
b10 .
b10 2
b10010 &
b10010 9
b10 6
b10 :
1,
#60
0,
#62
b10011 '
b10011 1
b11 .
b11 2
b10011 &
b10011 9
b11 6
b11 :
1,
#64
0,
#66
b10100 '
b10100 1
b100 .
b100 2
b10100 &
b10100 9
b100 6
b100 :
1,
#68
0,
#70
b10101 '
b10101 1
b101 .
b101 2
b10101 &
b10101 9
b101 6
b101 :
1,
#72
0,
#74
b10110 '
b10110 1
b110 .
b110 2
b10110 &
b10110 9
b110 6
b110 :
1,
#76
0,
#78
b10111 '
b10111 1
b111 .
b111 2
b10111 &
b10111 9
b111 6
b111 :
1,
#80
0,
#82
b11000 '
b11000 1
b1000 .
b1000 2
b11000 &
b11000 9
b1000 6
b1000 :
1,
#84
0,
#86
03
0;
10
b11001 '
b11001 1
b1001 .
b1001 2
18
b11001 &
b11001 9
b1001 6
b1001 :
1,
#88
0,
#90
b10 -
b10 4
b10 5
b10 <
13
1;
00
b100000 '
b100000 1
b0 .
b0 2
08
b100000 &
b100000 9
b0 6
b0 :
1,
#92
0,
#94
b100001 '
b100001 1
b1 .
b1 2
b100001 &
b100001 9
b1 6
b1 :
1,
#96
0,
#98
b100010 '
b100010 1
b10 .
b10 2
b100010 &
b100010 9
b10 6
b10 :
1,
#100
0,
#102
b100011 '
b100011 1
b11 .
b11 2
b100011 &
b100011 9
b11 6
b11 :
1,
#104
0,
#106
b100100 '
b100100 1
b100 .
b100 2
b100100 &
b100100 9
b100 6
b100 :
1,
#108
0,
#110
b100101 '
b100101 1
b101 .
b101 2
b100101 &
b100101 9
b101 6
b101 :
1,
#112
0,
#114
b100110 '
b100110 1
b110 .
b110 2
b100110 &
b100110 9
b110 6
b110 :
1,
#116
0,
#118
b100111 '
b100111 1
b111 .
b111 2
b100111 &
b100111 9
b111 6
b111 :
1,
#120
0,
#122
b101000 '
b101000 1
b1000 .
b1000 2
b101000 &
b101000 9
b1000 6
b1000 :
1,
#124
0,
#126
03
0;
10
b101001 '
b101001 1
b1001 .
b1001 2
18
b101001 &
b101001 9
b1001 6
b1001 :
1,
#128
0,
#130
b11 -
b11 4
b11 5
b11 <
13
1;
00
b110000 '
b110000 1
b0 .
b0 2
08
b110000 &
b110000 9
b0 6
b0 :
1,
#132
0,
#134
b110001 '
b110001 1
b1 .
b1 2
b110001 &
b110001 9
b1 6
b1 :
1,
#136
0,
#138
b110010 '
b110010 1
b10 .
b10 2
b110010 &
b110010 9
b10 6
b10 :
1,
#140
0,
#142
b110011 '
b110011 1
b11 .
b11 2
b110011 &
b110011 9
b11 6
b11 :
1,
#144
0,
#146
b110100 '
b110100 1
b100 .
b100 2
b110100 &
b110100 9
b100 6
b100 :
1,
#148
0,
#150
b110101 '
b110101 1
b101 .
b101 2
b110101 &
b110101 9
b101 6
b101 :
1,
#152
0,
#154
b110110 '
b110110 1
b110 .
b110 2
b110110 &
b110110 9
b110 6
b110 :
1,
#156
0,
#158
b110111 '
b110111 1
b111 .
b111 2
b110111 &
b110111 9
b111 6
b111 :
1,
#160
0,
#162
b111000 '
b111000 1
b1000 .
b1000 2
b111000 &
b111000 9
b1000 6
b1000 :
1,
#164
0,
#166
03
0;
10
b111001 '
b111001 1
b1001 .
b1001 2
18
b111001 &
b111001 9
b1001 6
b1001 :
1,
#168
0,
#170
b100 -
b100 4
b100 5
b100 <
13
1;
00
b1000000 '
b1000000 1
b0 .
b0 2
08
b1000000 &
b1000000 9
b0 6
b0 :
1,
#172
0,
#174
b1000001 '
b1000001 1
b1 .
b1 2
b1000001 &
b1000001 9
b1 6
b1 :
1,
#176
0,
#178
b1000010 '
b1000010 1
b10 .
b10 2
b1000010 &
b1000010 9
b10 6
b10 :
1,
#180
0,
#182
b1000011 '
b1000011 1
b11 .
b11 2
b1000011 &
b1000011 9
b11 6
b11 :
1,
#184
0,
#186
b1000100 '
b1000100 1
b100 .
b100 2
b1000100 &
b1000100 9
b100 6
b100 :
1,
#188
0,
#190
b1000101 '
b1000101 1
b101 .
b101 2
b1000101 &
b1000101 9
b101 6
b101 :
1,
#192
0,
#194
b1000110 '
b1000110 1
b110 .
b110 2
b1000110 &
b1000110 9
b110 6
b110 :
1,
#196
0,
#198
b1000111 '
b1000111 1
b111 .
b111 2
b1000111 &
b1000111 9
b111 6
b111 :
1,
#200
0,
#202
b1001000 '
b1001000 1
b1000 .
b1000 2
b1001000 &
b1001000 9
b1000 6
b1000 :
1,
#204
0,
#206
03
0;
10
b1001001 '
b1001001 1
b1001 .
b1001 2
18
b1001001 &
b1001001 9
b1001 6
b1001 :
1,
#208
0,
#210
b101 -
b101 4
b101 5
b101 <
13
1;
00
b1010000 '
b1010000 1
b0 .
b0 2
08
b1010000 &
b1010000 9
b0 6
b0 :
1,
#212
0,
#214
b1010001 '
b1010001 1
b1 .
b1 2
b1010001 &
b1010001 9
b1 6
b1 :
1,
#216
0,
#218
b1010010 '
b1010010 1
b10 .
b10 2
b1010010 &
b1010010 9
b10 6
b10 :
1,
#220
0,
#222
b1010011 '
b1010011 1
b11 .
b11 2
b1010011 &
b1010011 9
b11 6
b11 :
1,
#224
0,
#226
b1010100 '
b1010100 1
b100 .
b100 2
b1010100 &
b1010100 9
b100 6
b100 :
1,
#228
0,
#230
b1010101 '
b1010101 1
b101 .
b101 2
b1010101 &
b1010101 9
b101 6
b101 :
1,
#232
0,
#234
b1010110 '
b1010110 1
b110 .
b110 2
b1010110 &
b1010110 9
b110 6
b110 :
1,
#236
0,
#238
b1010111 '
b1010111 1
b111 .
b111 2
b1010111 &
b1010111 9
b111 6
b111 :
1,
#240
0,
#242
b1011000 '
b1011000 1
b1000 .
b1000 2
b1011000 &
b1011000 9
b1000 6
b1000 :
1,
#244
0,
#246
03
0;
10
b1011001 '
b1011001 1
b1001 .
b1001 2
18
b1011001 &
b1011001 9
b1001 6
b1001 :
1,
#248
0,
#250
b110 -
b110 4
b110 5
b110 <
13
1;
00
b1100000 '
b1100000 1
b0 .
b0 2
08
b1100000 &
b1100000 9
b0 6
b0 :
1,
#252
0,
#254
b1100001 '
b1100001 1
b1 .
b1 2
b1100001 &
b1100001 9
b1 6
b1 :
1,
#256
0,
#258
b1100010 '
b1100010 1
b10 .
b10 2
b1100010 &
b1100010 9
b10 6
b10 :
1,
#260
0,
#262
b1100011 '
b1100011 1
b11 .
b11 2
b1100011 &
b1100011 9
b11 6
b11 :
1,
#264
0,
#266
b1100100 '
b1100100 1
b100 .
b100 2
b1100100 &
b1100100 9
b100 6
b100 :
1,
#268
0,
#270
b1100101 '
b1100101 1
b101 .
b101 2
b1100101 &
b1100101 9
b101 6
b101 :
1,
#272
0,
#274
b1100110 '
b1100110 1
b110 .
b110 2
b1100110 &
b1100110 9
b110 6
b110 :
1,
#276
0,
#278
b1100111 '
b1100111 1
b111 .
b111 2
b1100111 &
b1100111 9
b111 6
b111 :
1,
#280
0,
#282
b1101000 '
b1101000 1
b1000 .
b1000 2
b1101000 &
b1101000 9
b1000 6
b1000 :
1,
#284
0,
#286
03
0;
10
b1101001 '
b1101001 1
b1001 .
b1001 2
18
b1101001 &
b1101001 9
b1001 6
b1001 :
1,
#288
0,
#290
b111 -
b111 4
b111 5
b111 <
13
1;
00
b1110000 '
b1110000 1
b0 .
b0 2
08
b1110000 &
b1110000 9
b0 6
b0 :
1,
#292
0,
#294
b1110001 '
b1110001 1
b1 .
b1 2
b1110001 &
b1110001 9
b1 6
b1 :
1,
#296
0,
#298
b1110010 '
b1110010 1
b10 .
b10 2
b1110010 &
b1110010 9
b10 6
b10 :
1,
#300
0,
#302
b1110011 '
b1110011 1
b11 .
b11 2
b1110011 &
b1110011 9
b11 6
b11 :
1,
#304
0,
#306
b1110100 '
b1110100 1
b100 .
b100 2
b1110100 &
b1110100 9
b100 6
b100 :
1,
#308
0,
#310
b1110101 '
b1110101 1
b101 .
b101 2
b1110101 &
b1110101 9
b101 6
b101 :
1,
#312
0,
#314
b1110110 '
b1110110 1
b110 .
b110 2
b1110110 &
b1110110 9
b110 6
b110 :
1,
#316
0,
#318
b1110111 '
b1110111 1
b111 .
b111 2
b1110111 &
b1110111 9
b111 6
b111 :
1,
#320
0,
#322
b1111000 '
b1111000 1
b1000 .
b1000 2
b1111000 &
b1111000 9
b1000 6
b1000 :
1,
#324
0,
#326
03
0;
10
b1111001 '
b1111001 1
b1001 .
b1001 2
18
b1111001 &
b1111001 9
b1001 6
b1001 :
1,
#328
0,
#330
b1000 -
b1000 4
b1000 5
b1000 <
13
1;
00
b10000000 '
b10000000 1
b0 .
b0 2
08
b10000000 &
b10000000 9
b0 6
b0 :
1,
#332
0,
#334
b10000001 '
b10000001 1
b1 .
b1 2
b10000001 &
b10000001 9
b1 6
b1 :
1,
#336
0,
#338
b10000010 '
b10000010 1
b10 .
b10 2
b10000010 &
b10000010 9
b10 6
b10 :
1,
#340
0,
#342
b10000011 '
b10000011 1
b11 .
b11 2
b10000011 &
b10000011 9
b11 6
b11 :
1,
#344
0,
#346
b10000100 '
b10000100 1
b100 .
b100 2
b10000100 &
b10000100 9
b100 6
b100 :
1,
#348
0,
#350
b10000101 '
b10000101 1
b101 .
b101 2
b10000101 &
b10000101 9
b101 6
b101 :
1,
#352
0,
#354
b10000110 '
b10000110 1
b110 .
b110 2
b10000110 &
b10000110 9
b110 6
b110 :
1,
#356
0,
#358
b10000111 '
b10000111 1
b111 .
b111 2
b10000111 &
b10000111 9
b111 6
b111 :
1,
#360
0,
#362
b10001000 '
b10001000 1
b1000 .
b1000 2
b10001000 &
b10001000 9
b1000 6
b1000 :
1,
#364
0,
#366
03
0;
10
b10001001 '
b10001001 1
b1001 .
b1001 2
18
b10001001 &
b10001001 9
b1001 6
b1001 :
1,
#368
0,
#370
1/
b1001 -
b1001 4
17
b1001 5
b1001 <
13
1;
00
b10010000 '
b10010000 1
b0 .
b0 2
08
b10010000 &
b10010000 9
b0 6
b0 :
1,
#372
0,
#374
b10010001 '
b10010001 1
b1 .
b1 2
b10010001 &
b10010001 9
b1 6
b1 :
1,
#376
0,
#378
b10010010 '
b10010010 1
b10 .
b10 2
b10010010 &
b10010010 9
b10 6
b10 :
1,
#380
0,
#382
b10010011 '
b10010011 1
b11 .
b11 2
b10010011 &
b10010011 9
b11 6
b11 :
1,
#384
0,
#386
b10010100 '
b10010100 1
b100 .
b100 2
b10010100 &
b10010100 9
b100 6
b100 :
1,
#388
0,
#390
b10010101 '
b10010101 1
b101 .
b101 2
b10010101 &
b10010101 9
b101 6
b101 :
1,
#392
0,
#394
b10010110 '
b10010110 1
b110 .
b110 2
b10010110 &
b10010110 9
b110 6
b110 :
1,
#396
0,
#398
b10010111 '
b10010111 1
b111 .
b111 2
b10010111 &
b10010111 9
b111 6
b111 :
1,
#400
0,
#402
b10011000 '
b10011000 1
b1000 .
b1000 2
b10011000 &
b10011000 9
b1000 6
b1000 :
1,
#404
0,
#406
1(
1)
03
0;
10
b10011001 '
b10011001 1
b1001 .
b1001 2
18
b10011001 &
b10011001 9
b1001 6
b1001 :
1,
#408
0,
#410
0/
b0 -
b0 4
07
b0 5
b0 <
0(
0)
13
1;
00
b0 '
b0 1
b0 .
b0 2
08
b0 &
b0 9
b0 6
b0 :
1,
#412
0,
#414
b1 '
b1 1
b1 .
b1 2
b1 &
b1 9
b1 6
b1 :
1,
#416
0,
#418
b10 '
b10 1
b10 .
b10 2
b10 &
b10 9
b10 6
b10 :
1,
#420
0,
#422
b11 '
b11 1
b11 .
b11 2
b11 &
b11 9
b11 6
b11 :
1,
#424
0,
#426
b100 '
b100 1
b100 .
b100 2
b100 &
b100 9
b100 6
b100 :
1,
#428
0,
#430
b101 '
b101 1
b101 .
b101 2
b101 &
b101 9
b101 6
b101 :
1,
#432
0,
#434
b110 '
b110 1
b110 .
b110 2
b110 &
b110 9
b110 6
b110 :
1,
#436
0,
#438
b111 '
b111 1
b111 .
b111 2
b111 &
b111 9
b111 6
b111 :
1,
#440
0,
#442
b1000 '
b1000 1
b1000 .
b1000 2
b1000 &
b1000 9
b1000 6
b1000 :
1,
#444
0,
#446
03
0;
10
b1001 '
b1001 1
b1001 .
b1001 2
18
b1001 &
b1001 9
b1001 6
b1001 :
1,
#448
0,
#450
b1 -
b1 4
b1 5
b1 <
13
1;
00
b10000 '
b10000 1
b0 .
b0 2
08
b10000 &
b10000 9
b0 6
b0 :
1,
#452
0,
#454
b10001 '
b10001 1
b1 .
b1 2
b10001 &
b10001 9
b1 6
b1 :
1,
#456
0,
#458
b10010 '
b10010 1
b10 .
b10 2
b10010 &
b10010 9
b10 6
b10 :
1,
#460
0,
#462
b10011 '
b10011 1
b11 .
b11 2
b10011 &
b10011 9
b11 6
b11 :
1,
#464
0,
#466
b10100 '
b10100 1
b100 .
b100 2
b10100 &
b10100 9
b100 6
b100 :
1,
#468
0,
#470
b10101 '
b10101 1
b101 .
b101 2
b10101 &
b10101 9
b101 6
b101 :
1,
#472
0,
#474
b10110 '
b10110 1
b110 .
b110 2
b10110 &
b10110 9
b110 6
b110 :
1,
#476
0,
#478
b10111 '
b10111 1
b111 .
b111 2
b10111 &
b10111 9
b111 6
b111 :
1,
#480
0,
#482
b11000 '
b11000 1
b1000 .
b1000 2
b11000 &
b11000 9
b1000 6
b1000 :
1,
#484
0,
#486
03
0;
10
b11001 '
b11001 1
b1001 .
b1001 2
18
b11001 &
b11001 9
b1001 6
b1001 :
1,
#488
0,
#490
b10 -
b10 4
b10 5
b10 <
13
1;
00
b100000 '
b100000 1
b0 .
b0 2
08
b100000 &
b100000 9
b0 6
b0 :
1,
#492
0,
#494
b100001 '
b100001 1
b1 .
b1 2
b100001 &
b100001 9
b1 6
b1 :
1,
#496
0,
#498
b100010 '
b100010 1
b10 .
b10 2
b100010 &
b100010 9
b10 6
b10 :
1,
#500
0,
#502
b100011 '
b100011 1
b11 .
b11 2
b100011 &
b100011 9
b11 6
b11 :
1,
#504
0,
#506
b100100 '
b100100 1
b100 .
b100 2
b100100 &
b100100 9
b100 6
b100 :
1,
#508
0,
#510
b100101 '
b100101 1
b101 .
b101 2
b100101 &
b100101 9
b101 6
b101 :
1,
