examX/alu_n.v
module FA (a,b,ci,s,co);
  input a,b,ci;
  output s,co;
  assign s = a^b^ci;
  assign co = a&b|b&ci|ci&a;
endmodule

module FA4b5b (a, b, mo, c);
    input [3:0] a,b;
    input mo;
    //0:plus, 1:minus
    output [4:0] c;
    wire c1, c2, c3, c4;

    FA f1 (a[0], b[0]^mo, mo, c[0], c1);
    FA f2 (a[1], b[1]^mo, c1, c[1], c2);
    FA f3 (a[2], b[2]^mo, c2, c[2], c3);
    FA f4 (a[3], b[3]^mo, c3, c[3], c4);
    assign c[4] = c4^mo;
endmodule

module MULTI1x4 (a,b,s);
    input [3:0] a;
    input b;
    output [3:0] s;

    assign s = {a[3]&b, a[2]&b, a[1]&b, a[0]&b};
endmodule

module MULTI4b8b (a,b,s);
    input [3:0] a,b;
    output [7:0] s;
    wire [3:0] ab0, ab1, ab2, ab3;
    wire [4:0] c1, c2, c3;

    MULTI1x4 m0 (a, b[0], ab0);
    MULTI1x4 m1 (a, b[1], ab1);
    MULTI1x4 m2 (a, b[2], ab2);
    MULTI1x4 m3 (a, b[3], ab3);

    assign s[0] = a[0]&b[0];
    FA4b5b f1 (.a({1'b0,ab0[3:1]}), .b(ab1), .mo(1'b0), .c(c1));
    assign s[1] = c1[0];
    FA4b5b f2 (.a(c1[4:1]), .b(ab2), .mo(1'b0), .c(c2));
    assign s[2] = c2[0];
    FA4b5b f3 (.a(c2[4:1]), .b(ab3), .mo(1'b0), .c(s[7:3]));
endmodule

module comp4 (a,b,s);
    input[3:0] a,b;
    output [1:0] s;

    assign s =
        (a[3]&~b[3]) ? 2'b10 :
        (~a[3]&b[3]) ? 2'b01 :
        (a[2]&~b[2]) ? 2'b10 :
        (~a[2]&b[2]) ? 2'b01 :
        (a[1]&~b[1]) ? 2'b10 :
        (~a[1]&b[1]) ? 2'b01 :
        (a[0]&~b[0]) ? 2'b10 :
        (~a[0]&b[0]) ? 2'b01 : 2'b11;
endmodule

module lshift (a,c,s);
    input [3:0] a;
    input [1:0] c;
    output [3:0] s;

    function [3:0] lshifter;
        input [3:0] a;
        input [1:0] c;

        case (c)
            2'b11 : lshifter = {a[0],3'b000};
            2'b10 : lshifter = {a[1:0],2'b00};
            2'b01 : lshifter = {a[2:0],1'b0};
            2'b00 : lshifter = {a};
            default : lshifter = 4'b000;
        endcase
    endfunction

    assign s = lshifter(a, c);
endmodule

module div4once(a, b, c, ar, sr);
// a: 割られる数, b:割る数, c:シフト数,  , ar:余り, sr:商
    input [3:0] a, b;
    input [1:0] c;
    output [3:0] ar, sr;

    wire [3:0] bx;
    wire [1:0] cy;
    wire [4:0] arf;
    wire [3:0] sw;

    lshift lc (b, c, bx);
    comp4 cxv (a, bx, cy);
    FA4b5b fx (a, bx, 1'b1, arf);
    lshift ls (4'b0001, c, sw);

    assign sr = cy[1] ? sw : 4'b0000;
    assign ar = cy[1] ? arf[3:0] : a;
endmodule

module div4 (a,b,s,r);
    input [3:0] a, b;
    output [3:0] s, r;

    wire [3:0] av3,av2,av1,av0;
    wire [3:0] sv3,sv2,sv1,sv0;
    wire [7:0] as3, as2, as1, as0;

    div4once d3 (a  , b, 2'b11, av3, sv3);
    assign as3 = (~(b[3]|b[2]|b[1]))
        ? {av3, 4'b0000 | sv3}
        : {a, 4'b0000};

    div4once d2 (as3 [7:4], b, 2'b10, av2, sv2);
    assign as2 = (~(b[3]|b[2]))
        ? {av2, as3 [3:0] | sv2}
        : as3;

    div4once d1 (as2 [7:4], b, 2'b01, av1, sv1);
    assign as1 = (~(b[3]))
        ? {av1, as2 [3:0] | sv1}
        : as2;

    div4once d0 (as1 [7:4], b, 2'b00, av0, sv0);

    assign r = av0;
    assign s = as1 [3:0] | sv0;
endmodule

module ALU (a, b, f, CLK, CLR, v, y);
    input [3:0] a,b;
    input [4:0] f;
    input CLK, CLR, v;
    output [3:0] y;
    reg [3:0] y;
    reg state;

    wire [4:0] adder, minus;
    FA4b5b p4 (a, b, 1'b0, adder);
    FA4b5b d4 (a, b, 1'b1, minus);

    wire [7:0] multi;
    MULTI4b8b m4 (a, b, multi);

    wire [3:0] divis, remai;
    div4 di4 (a, b, divis, remai);
// or
    always @ (posedge CLK, negedge CLR) begin
        if (CLR==1'b0) begin
            state = 1'b1;
            y = 4'b0000;
        end else begin
            state = 1'b0;
            case (f)
                5'b00010 : y = v ? {3'b000, adder[4]} : adder[3:0]; //足し算
                5'b00011 : y = v ? {minus[4], minus[4], minus[4], minus[4]} : minus[3:0]; //引き算
                5'b01000 : y = a&b; //AND
                5'b01100 : y = a|b; //OR
                5'b00000 : y = {a[2:0], 1'b0}; //左シフト
                5'b10000 : y = {1'b0, a[3:1]}; //右シフト
                5'b00100 : y = v ? multi[7:4] : multi[3:0]; //掛け算
                5'b00110 : y = v ? remai : divis; //割り算
                default  : y = 4'b0000;
            endcase
        end
    end
endmodule

module ALU_test;
    reg [3:0] a, b;
    reg [4:0] f;
    reg clk, clr, v;
    wire [3:0] c;

    ALU mainALU (a, b, f, clk, clr, v, c);

    initial begin;
        $dumpfile("alun.vcd");    // CKTKWave による波形表示のためのシミュレーション結果出力ファイル名指定
        $dumpvars(0);        // すべての信号を表示対象とするための設定
        $monitor("%4t a:%d b:%d f:%b CLK:%b CLR:%b v:%d c:%b", $time, a, b, f, clk, clr, v, c);    // 表示設定

        #0
        clr=1;
        a = 4'b1110;
        b = 4'b0110;
        v=1'b1;
        clk=0;
        #1
        clr=0;
        #1
        clr=1;
        #2
        f=5'b00010;
        #10
        v=1'b0;
        #10
        v=1'b1;
        f=5'b00011;
        #10
        v=1'b0;
        #10
        f=5'b01000;
        #10
        f=5'b01100;
        #10
        f=5'b00000;
        #10
        f=5'b10000;
        #10
        v=1'b1;
        f=5'b00100;
        #10
        v=1'b0;
        #10
        f=5'b00110;
        #10
        v=1'b1;
        #10
        f=5'b11111;


        #0
        a = 4'b0110;
        b = 4'b1010;
        clr=0;
        #2
        clr=1;
        #3
        v=1'b1;
        f=5'b11111;
        #10
        v=1'b1;
        f=5'b00010;
        #10
        v=1'b0;
        #10
        v=1'b1;
        f=5'b00011;
        #10
        v=1'b0;
        #10
        f=5'b01000;
        #10
        f=5'b01100;
        #10
        f=5'b00000;
        #10
        f=5'b10000;
        #10
        v=1'b1;
        f=5'b00100;
        #10
        v=1'b0;
        #10
        f=5'b00110;
        #10
        v=1'b1;
        #10
        f=5'b11111;
        #10 $finish;
    end                // シミュレーションの終了指示

    always #(5)
        clk <= ~clk;
endmodule

examX/alun.vcd
$date
	Sat Jul 25 13:50:39 2020
$end
$version
	Icarus Verilog
$end
$timescale
	1s
$end
$scope module ALU_test $end
$var wire 4 ! c [3:0] $end
$var reg 4 " a [3:0] $end
$var reg 4 # b [3:0] $end
$var reg 1 $ clk $end
$var reg 1 % clr $end
$var reg 5 & f [4:0] $end
$var reg 1 ' v $end
$scope module mainALU $end
$var wire 1 $ CLK $end
$var wire 1 % CLR $end
$var wire 4 ( a [3:0] $end
$var wire 4 ) b [3:0] $end
$var wire 5 * f [4:0] $end
$var wire 1 ' v $end
$var wire 4 + remai [3:0] $end
$var wire 8 , multi [7:0] $end
$var wire 5 - minus [4:0] $end
$var wire 4 . divis [3:0] $end
$var wire 5 / adder [4:0] $end
$var reg 1 0 state $end
$var reg 4 1 y [3:0] $end
$scope module d4 $end
$var wire 4 2 a [3:0] $end
$var wire 4 3 b [3:0] $end
$var wire 1 4 mo $end
$var wire 1 5 c4 $end
$var wire 1 6 c3 $end
$var wire 1 7 c2 $end
$var wire 1 8 c1 $end
$var wire 5 9 c [4:0] $end
$scope module f1 $end
$var wire 1 : a $end
$var wire 1 ; b $end
$var wire 1 4 ci $end
$var wire 1 8 co $end
$var wire 1 < s $end
$upscope $end
$scope module f2 $end
$var wire 1 = a $end
$var wire 1 > b $end
$var wire 1 8 ci $end
$var wire 1 7 co $end
$var wire 1 ? s $end
$upscope $end
$scope module f3 $end
$var wire 1 @ a $end
$var wire 1 A b $end
$var wire 1 7 ci $end
$var wire 1 6 co $end
$var wire 1 B s $end
$upscope $end
$scope module f4 $end
$var wire 1 C a $end
$var wire 1 D b $end
$var wire 1 6 ci $end
$var wire 1 5 co $end
$var wire 1 E s $end
$upscope $end
$upscope $end
$scope module di4 $end
$var wire 4 F a [3:0] $end
$var wire 4 G b [3:0] $end
$var wire 4 H r [3:0] $end
$var wire 4 I s [3:0] $end
$var wire 4 J sv3 [3:0] $end
$var wire 4 K sv2 [3:0] $end
$var wire 4 L sv1 [3:0] $end
$var wire 4 M sv0 [3:0] $end
$var wire 4 N av3 [3:0] $end
$var wire 4 O av2 [3:0] $end
$var wire 4 P av1 [3:0] $end
$var wire 4 Q av0 [3:0] $end
$var wire 8 R as3 [7:0] $end
$var wire 8 S as2 [7:0] $end
$var wire 8 T as1 [7:0] $end
$scope module d0 $end
$var wire 4 U a [3:0] $end
$var wire 4 V b [3:0] $end
$var wire 2 W c [1:0] $end
$var wire 4 X sw [3:0] $end
$var wire 4 Y sr [3:0] $end
$var wire 2 Z cy [1:0] $end
$var wire 4 [ bx [3:0] $end
$var wire 5 \ arf [4:0] $end
$var wire 4 ] ar [3:0] $end
$scope module cxv $end
$var wire 4 ^ a [3:0] $end
$var wire 2 _ s [1:0] $end
$var wire 4 ` b [3:0] $end
$upscope $end
$scope module fx $end
$var wire 4 a a [3:0] $end
$var wire 1 b mo $end
$var wire 1 c c4 $end
$var wire 1 d c3 $end
$var wire 1 e c2 $end
$var wire 1 f c1 $end
$var wire 5 g c [4:0] $end
$var wire 4 h b [3:0] $end
$scope module f1 $end
$var wire 1 i a $end
$var wire 1 j b $end
$var wire 1 b ci $end
$var wire 1 f co $end
$var wire 1 k s $end
$upscope $end
$scope module f2 $end
$var wire 1 l a $end
$var wire 1 m b $end
$var wire 1 f ci $end
$var wire 1 e co $end
$var wire 1 n s $end
$upscope $end
$scope module f3 $end
$var wire 1 o a $end
$var wire 1 p b $end
$var wire 1 e ci $end
$var wire 1 d co $end
$var wire 1 q s $end
$upscope $end
$scope module f4 $end
$var wire 1 r a $end
$var wire 1 s b $end
$var wire 1 d ci $end
$var wire 1 c co $end
$var wire 1 t s $end
$upscope $end
$upscope $end
$scope module lc $end
$var wire 4 u a [3:0] $end
$var wire 2 v c [1:0] $end
$var wire 4 w s [3:0] $end
$scope function lshifter $end
$var reg 4 x a [3:0] $end
$var reg 2 y c [1:0] $end
$var reg 4 z lshifter [3:0] $end
$upscope $end
$upscope $end
$scope module ls $end
$var wire 4 { a [3:0] $end
$var wire 2 | c [1:0] $end
$var wire 4 } s [3:0] $end
$scope function lshifter $end
$var reg 4 ~ a [3:0] $end
$var reg 2 !" c [1:0] $end
$var reg 4 "" lshifter [3:0] $end
$upscope $end
$upscope $end
$upscope $end
$scope module d1 $end
$var wire 4 #" a [3:0] $end
$var wire 4 $" b [3:0] $end
$var wire 2 %" c [1:0] $end
$var wire 4 &" sw [3:0] $end
$var wire 4 '" sr [3:0] $end
$var wire 2 (" cy [1:0] $end
$var wire 4 )" bx [3:0] $end
$var wire 5 *" arf [4:0] $end
$var wire 4 +" ar [3:0] $end
$scope module cxv $end
$var wire 4 ," a [3:0] $end
$var wire 2 -" s [1:0] $end
$var wire 4 ." b [3:0] $end
$upscope $end
$scope module fx $end
$var wire 4 /" a [3:0] $end
$var wire 1 0" mo $end
$var wire 1 1" c4 $end
$var wire 1 2" c3 $end
$var wire 1 3" c2 $end
$var wire 1 4" c1 $end
$var wire 5 5" c [4:0] $end
$var wire 4 6" b [3:0] $end
$scope module f1 $end
$var wire 1 7" a $end
$var wire 1 8" b $end
$var wire 1 0" ci $end
$var wire 1 4" co $end
$var wire 1 9" s $end
$upscope $end
$scope module f2 $end
$var wire 1 :" a $end
$var wire 1 ;" b $end
$var wire 1 4" ci $end
$var wire 1 3" co $end
$var wire 1 <" s $end
$upscope $end
$scope module f3 $end
$var wire 1 =" a $end
$var wire 1 >" b $end
$var wire 1 3" ci $end
$var wire 1 2" co $end
$var wire 1 ?" s $end
$upscope $end
$scope module f4 $end
$var wire 1 @" a $end
$var wire 1 A" b $end
$var wire 1 2" ci $end
$var wire 1 1" co $end
$var wire 1 B" s $end
$upscope $end
$upscope $end
$scope module lc $end
$var wire 4 C" a [3:0] $end
$var wire 2 D" c [1:0] $end
$var wire 4 E" s [3:0] $end
$scope function lshifter $end
$var reg 4 F" a [3:0] $end
$var reg 2 G" c [1:0] $end
$var reg 4 H" lshifter [3:0] $end
$upscope $end
$upscope $end
$scope module ls $end
$var wire 4 I" a [3:0] $end
$var wire 2 J" c [1:0] $end
$var wire 4 K" s [3:0] $end
$scope function lshifter $end
$var reg 4 L" a [3:0] $end
$var reg 2 M" c [1:0] $end
$var reg 4 N" lshifter [3:0] $end
$upscope $end
$upscope $end
$upscope $end
$scope module d2 $end
$var wire 4 O" a [3:0] $end
$var wire 4 P" b [3:0] $end
$var wire 2 Q" c [1:0] $end
$var wire 4 R" sw [3:0] $end
$var wire 4 S" sr [3:0] $end
$var wire 2 T" cy [1:0] $end
$var wire 4 U" bx [3:0] $end
$var wire 5 V" arf [4:0] $end
$var wire 4 W" ar [3:0] $end
$scope module cxv $end
$var wire 4 X" a [3:0] $end
$var wire 2 Y" s [1:0] $end
$var wire 4 Z" b [3:0] $end
$upscope $end
$scope module fx $end
$var wire 4 [" a [3:0] $end
$var wire 1 \" mo $end
$var wire 1 ]" c4 $end
$var wire 1 ^" c3 $end
$var wire 1 _" c2 $end
$var wire 1 `" c1 $end
$var wire 5 a" c [4:0] $end
$var wire 4 b" b [3:0] $end
$scope module f1 $end
$var wire 1 c" a $end
$var wire 1 d" b $end
$var wire 1 \" ci $end
$var wire 1 `" co $end
$var wire 1 e" s $end
$upscope $end
$scope module f2 $end
$var wire 1 f" a $end
$var wire 1 g" b $end
$var wire 1 `" ci $end
$var wire 1 _" co $end
$var wire 1 h" s $end
$upscope $end
$scope module f3 $end
$var wire 1 i" a $end
$var wire 1 j" b $end
$var wire 1 _" ci $end
$var wire 1 ^" co $end
$var wire 1 k" s $end
$upscope $end
$scope module f4 $end
$var wire 1 l" a $end
$var wire 1 m" b $end
$var wire 1 ^" ci $end
$var wire 1 ]" co $end
$var wire 1 n" s $end
$upscope $end
$upscope $end
$scope module lc $end
$var wire 4 o" a [3:0] $end
$var wire 2 p" c [1:0] $end
$var wire 4 q" s [3:0] $end
$scope function lshifter $end
$var reg 4 r" a [3:0] $end
$var reg 2 s" c [1:0] $end
$var reg 4 t" lshifter [3:0] $end
$upscope $end
$upscope $end
$scope module ls $end
$var wire 4 u" a [3:0] $end
$var wire 2 v" c [1:0] $end
$var wire 4 w" s [3:0] $end
$scope function lshifter $end
$var reg 4 x" a [3:0] $end
$var reg 2 y" c [1:0] $end
$var reg 4 z" lshifter [3:0] $end
$upscope $end
$upscope $end
$upscope $end
$scope module d3 $end
$var wire 4 {" a [3:0] $end
$var wire 4 |" b [3:0] $end
$var wire 2 }" c [1:0] $end
$var wire 4 ~" sw [3:0] $end
$var wire 4 !# sr [3:0] $end
$var wire 2 "# cy [1:0] $end
$var wire 4 ## bx [3:0] $end
$var wire 5 $# arf [4:0] $end
$var wire 4 %# ar [3:0] $end
$scope module cxv $end
$var wire 4 &# a [3:0] $end
$var wire 2 '# s [1:0] $end
$var wire 4 (# b [3:0] $end
$upscope $end
$scope module fx $end
$var wire 4 )# a [3:0] $end
$var wire 1 *# mo $end
$var wire 1 +# c4 $end
$var wire 1 ,# c3 $end
$var wire 1 -# c2 $end
$var wire 1 .# c1 $end
$var wire 5 /# c [4:0] $end
$var wire 4 0# b [3:0] $end
$scope module f1 $end
$var wire 1 1# a $end
$var wire 1 2# b $end
$var wire 1 *# ci $end
$var wire 1 .# co $end
$var wire 1 3# s $end
$upscope $end
$scope module f2 $end
$var wire 1 4# a $end
$var wire 1 5# b $end
$var wire 1 .# ci $end
$var wire 1 -# co $end
$var wire 1 6# s $end
$upscope $end
$scope module f3 $end
$var wire 1 7# a $end
$var wire 1 8# b $end
$var wire 1 -# ci $end
$var wire 1 ,# co $end
$var wire 1 9# s $end
$upscope $end
$scope module f4 $end
$var wire 1 :# a $end
$var wire 1 ;# b $end
$var wire 1 ,# ci $end
$var wire 1 +# co $end
$var wire 1 <# s $end
$upscope $end
$upscope $end
$scope module lc $end
$var wire 4 =# a [3:0] $end
$var wire 2 ># c [1:0] $end
$var wire 4 ?# s [3:0] $end
$scope function lshifter $end
$var reg 4 @# a [3:0] $end
$var reg 2 A# c [1:0] $end
$var reg 4 B# lshifter [3:0] $end
$upscope $end
$upscope $end
$scope module ls $end
$var wire 4 C# a [3:0] $end
$var wire 2 D# c [1:0] $end
$var wire 4 E# s [3:0] $end
$scope function lshifter $end
$var reg 4 F# a [3:0] $end
$var reg 2 G# c [1:0] $end
$var reg 4 H# lshifter [3:0] $end
$upscope $end
$upscope $end
$upscope $end
$upscope $end
$scope module m4 $end
$var wire 4 I# a [3:0] $end
$var wire 4 J# b [3:0] $end
$var wire 8 K# s [7:0] $end
$var wire 5 L# c2 [4:0] $end
$var wire 5 M# c1 [4:0] $end
$var wire 4 N# ab3 [3:0] $end
$var wire 4 O# ab2 [3:0] $end
$var wire 4 P# ab1 [3:0] $end
$var wire 4 Q# ab0 [3:0] $end
$scope module f1 $end
$var wire 4 R# a [3:0] $end
$var wire 1 S# mo $end
$var wire 1 T# c4 $end
$var wire 1 U# c3 $end
$var wire 1 V# c2 $end
$var wire 1 W# c1 $end
$var wire 5 X# c [4:0] $end
$var wire 4 Y# b [3:0] $end
$scope module f1 $end
$var wire 1 Z# a $end
$var wire 1 [# b $end
$var wire 1 S# ci $end
$var wire 1 W# co $end
$var wire 1 \# s $end
$upscope $end
$scope module f2 $end
$var wire 1 ]# a $end
$var wire 1 ^# b $end
$var wire 1 W# ci $end
$var wire 1 V# co $end
$var wire 1 _# s $end
$upscope $end
$scope module f3 $end
$var wire 1 `# a $end
$var wire 1 a# b $end
$var wire 1 V# ci $end
$var wire 1 U# co $end
$var wire 1 b# s $end
$upscope $end
$scope module f4 $end
$var wire 1 c# a $end
$var wire 1 d# b $end
$var wire 1 U# ci $end
$var wire 1 T# co $end
$var wire 1 e# s $end
$upscope $end
$upscope $end
$scope module f2 $end
$var wire 4 f# a [3:0] $end
$var wire 1 g# mo $end
$var wire 1 h# c4 $end
$var wire 1 i# c3 $end
$var wire 1 j# c2 $end
$var wire 1 k# c1 $end
$var wire 5 l# c [4:0] $end
$var wire 4 m# b [3:0] $end
$scope module f1 $end
$var wire 1 n# a $end
$var wire 1 o# b $end
$var wire 1 g# ci $end
$var wire 1 k# co $end
$var wire 1 p# s $end
$upscope $end
$scope module f2 $end
$var wire 1 q# a $end
$var wire 1 r# b $end
$var wire 1 k# ci $end
$var wire 1 j# co $end
$var wire 1 s# s $end
$upscope $end
$scope module f3 $end
$var wire 1 t# a $end
$var wire 1 u# b $end
$var wire 1 j# ci $end
$var wire 1 i# co $end
$var wire 1 v# s $end
$upscope $end
$scope module f4 $end
$var wire 1 w# a $end
$var wire 1 x# b $end
$var wire 1 i# ci $end
$var wire 1 h# co $end
$var wire 1 y# s $end
$upscope $end
$upscope $end
$scope module f3 $end
$var wire 4 z# a [3:0] $end
$var wire 1 {# mo $end
$var wire 1 |# c4 $end
$var wire 1 }# c3 $end
$var wire 1 ~# c2 $end
$var wire 1 !$ c1 $end
$var wire 5 "$ c [4:0] $end
$var wire 4 #$ b [3:0] $end
$scope module f1 $end
$var wire 1 $$ a $end
$var wire 1 %$ b $end
$var wire 1 {# ci $end
$var wire 1 !$ co $end
$var wire 1 &$ s $end
$upscope $end
$scope module f2 $end
$var wire 1 '$ a $end
$var wire 1 ($ b $end
$var wire 1 !$ ci $end
$var wire 1 ~# co $end
$var wire 1 )$ s $end
$upscope $end
$scope module f3 $end
$var wire 1 *$ a $end
$var wire 1 +$ b $end
$var wire 1 ~# ci $end
$var wire 1 }# co $end
$var wire 1 ,$ s $end
$upscope $end
$scope module f4 $end
$var wire 1 -$ a $end
$var wire 1 .$ b $end
$var wire 1 }# ci $end
$var wire 1 |# co $end
$var wire 1 /$ s $end
$upscope $end
$upscope $end
$scope module m0 $end
$var wire 4 0$ a [3:0] $end
$var wire 1 1$ b $end
$var wire 4 2$ s [3:0] $end
$upscope $end
$scope module m1 $end
$var wire 4 3$ a [3:0] $end
$var wire 1 4$ b $end
$var wire 4 5$ s [3:0] $end
$upscope $end
$scope module m2 $end
$var wire 4 6$ a [3:0] $end
$var wire 1 7$ b $end
$var wire 4 8$ s [3:0] $end
$upscope $end
$scope module m3 $end
$var wire 4 9$ a [3:0] $end
$var wire 1 :$ b $end
$var wire 4 ;$ s [3:0] $end
$upscope $end
$upscope $end
$scope module p4 $end
$var wire 4 <$ a [3:0] $end
$var wire 4 =$ b [3:0] $end
$var wire 1 >$ mo $end
$var wire 1 ?$ c4 $end
$var wire 1 @$ c3 $end
$var wire 1 A$ c2 $end
$var wire 1 B$ c1 $end
$var wire 5 C$ c [4:0] $end
$scope module f1 $end
$var wire 1 D$ a $end
$var wire 1 E$ b $end
$var wire 1 >$ ci $end
$var wire 1 B$ co $end
$var wire 1 F$ s $end
$upscope $end
$scope module f2 $end
$var wire 1 G$ a $end
$var wire 1 H$ b $end
$var wire 1 B$ ci $end
$var wire 1 A$ co $end
$var wire 1 I$ s $end
$upscope $end
$scope module f3 $end
$var wire 1 J$ a $end
$var wire 1 K$ b $end
$var wire 1 A$ ci $end
$var wire 1 @$ co $end
$var wire 1 L$ s $end
$upscope $end
$scope module f4 $end
$var wire 1 M$ a $end
$var wire 1 N$ b $end
$var wire 1 @$ ci $end
$var wire 1 ?$ co $end
$var wire 1 O$ s $end
$upscope $end
$upscope $end
$upscope $end
$upscope $end
$enddefinitions $end
#0
$dumpvars
0O$
0N$
1M$
1L$
1K$
1J$
0I$
1H$
1G$
0F$
0E$
0D$
b10100 C$
0B$
1A$
1@$
1?$
0>$
b110 =$
b1110 <$
b0 ;$
0:$
b1110 9$
b1110 8$
17$
b1110 6$
b1110 5$
14$
b1110 3$
b0 2$
01$
b1110 0$
1/$
0.$
1-$
0,$
0+$
0*$
1)$
0($
1'$
0&$
0%$
0$$
b0 #$
b1010 "$
0!$
0~#
0}#
0|#
0{#
b1010 z#
0y#
1x#
0w#
1v#
1u#
1t#
0s#
1r#
1q#
1p#
0o#
1n#
b1110 m#
b10101 l#
0k#
1j#
1i#
1h#
0g#
b111 f#
1e#
1d#
0c#
1b#
1a#
0`#
1_#
1^#
0]#
0\#
0[#
0Z#
b1110 Y#
b1110 X#
0W#
0V#
0U#
0T#
0S#
b0 R#
b0 Q#
b1110 P#
b1110 O#
b0 N#
b1110 M#
b10101 L#
b1010100 K#
b110 J#
b1110 I#
b1000 H#
b11 G#
b1 F#
b1000 E#
b11 D#
b1 C#
b0 B#
b11 A#
b110 @#
b0 ?#
b11 >#
b110 =#
1<#
1;#
1:#
19#
18#
17#
16#
15#
14#
03#
12#
01#
b0 0#
b1110 /#
1.#
1-#
1,#
1+#
1*#
b1110 )#
b0 (#
b10 '#
b1110 &#
b1110 %#
b1110 $#
b0 ##
b10 "#
b1000 !#
b1000 ~"
b11 }"
b110 |"
b1110 {"
b100 z"
b10 y"
b1 x"
b100 w"
b10 v"
b1 u"
b1000 t"
b10 s"
b110 r"
b1000 q"
b10 p"
b110 o"
0n"
0m"
1l"
1k"
1j"
1i"
1h"
1g"
1f"
0e"
1d"
0c"
b1000 b"
b110 a"
1`"
1_"
1^"
1]"
1\"
b1110 ["
b1000 Z"
b10 Y"
b1110 X"
b110 W"
b110 V"
b1000 U"
b10 T"
b100 S"
b100 R"
b10 Q"
b110 P"
b1110 O"
b10 N"
b1 M"
b1 L"
b10 K"
b1 J"
b1 I"
b1100 H"
b1 G"
b110 F"
b1100 E"
b1 D"
b110 C"
0B"
0A"
1@"
0?"
0>"
1="
1<"
1;"
1:"
09"
18"
07"
b1100 6"
b10 5"
14"
13"
12"
11"
10"
b1110 /"
b1100 ."
b10 -"
b1110 ,"
b10 +"
b10 *"
b1100 )"
b10 ("
b10 '"
b10 &"
b1 %"
b110 $"
b1110 #"
b1 ""
b0 !"
b1 ~
b1 }
b0 |
b1 {
b110 z
b0 y
b110 x
b110 w
b0 v
b110 u
1t
1s
0r
1q
0p
0o
0n
0m
1l
0k
1j
0i
b110 h
b11100 g
1f
1e
0d
0c
1b
b10 a
b110 `
b1 _
b10 ^
b10 ]
b11100 \
b110 [
b1 Z
b0 Y
b1 X
b0 W
b110 V
b10 U
b100010 T
b11100000 S
b11100000 R
b10 Q
b10 P
b110 O
b1110 N
b0 M
b10 L
b100 K
b1000 J
b10 I
b10 H
b110 G
b1110 F
1E
1D
1C
0B
0A
1@
0?
0>
1=
0<
1;
0:
b1000 9
18
17
16
15
14
b110 3
b1110 2
bx 1
x0
b10100 /
b10 .
b1000 -
b1010100 ,
b10 +
bx *
b110 )
b1110 (
1'
bx &
1%
0$
b110 #
b1110 "
bx !
$end
#1
b0 !
b0 1
10
0%
#2
1%
#4
b10 &
b10 *
#5
b1 !
b1 1
00
1$
#10
0$
#14
0'
#15
b100 !
b100 1
1$
#20
0$
#24
b11 &
b11 *
1'
#25
b0 !
b0 1
1$
#30
0$
#34
0'
#35
b1000 !
b1000 1
1$
#40
0$
#44
b1000 &
b1000 *
#45
b110 !
b110 1
1$
#50
0$
#54
b1100 &
b1100 *
#55
b1110 !
b1110 1
1$
#60
0$
#64
b0 &
b0 *
#65
b1100 !
b1100 1
1$
#70
0$
#74
b10000 &
b10000 *
#75
b111 !
b111 1
1$
#80
0$
#84
b100 &
b100 *
1'
#85
b101 !
b101 1
1$
#90
0$
#94
0'
#95
b100 !
b100 1
1$
#100
0$
#104
b110 &
b110 *
#105
b10 !
b10 1
1$
#110
0$
#114
1'
#115
1$
#120
0$
#124
0/$
1&$
0-$
0i#
0}#
b0 K
b0 S"
0t#
1$$
0'$
0*$
0j#
0~#
b1 T"
b1 Y"
b110 O
b110 W"
b11 f#
b1 z#
0h#
1d
0v#
1s#
1,$
b111100 ,
b111100 K#
b111 "$
1)$
b110 M#
b110 X#
0e#
b11 L#
b11 l#
0y#
05
b110 +
b110 H
b110 Q
b110 ]
1o
b0 .
b0 I
1t
b11100 \
b11100 g
1q
b11110 V"
b11110 a"
1n"
0]"
b110 N
b110 %#
1B
b110 U
b110 ^
b110 a
0u#
0r#
1+$
1($
0L$
0@"
0d#
0x#
b1100000 T
0s
1p
1A"
b11100 -
b11100 9
1E
0l"
b110 #"
b110 ,"
b110 /"
b110 $#
b110 /#
0<#
b10000 /
b10000 C$
0O$
1?$
1A
0D
b110 N#
b110 #$
b110 ;$
0K$
1N$
b110 O"
b110 X"
b110 ["
b1100000 S
b110 P#
b110 Y#
b110 5$
b0 O#
b0 m#
b0 8$
b0 !
b0 1
10
b1010 [
b1010 `
b1010 h
b1010 w
b1010 z
b1010 x
b100 )"
b100 ."
b100 6"
b100 E"
b100 H"
b1010 F"
b1010 r"
b1010 @#
07$
1:$
0C
b1100000 R
0:#
0M$
0%
b1010 #
b1010 )
b1010 3
b1010 G
b1010 V
b1010 u
b1010 $"
b1010 C"
b1010 P"
b1010 o"
b1010 |"
b1010 =#
b1010 J#
b1010 =$
b110 "
b110 (
b110 2
b110 F
b110 {"
b110 &#
b110 )#
b110 I#
b110 0$
b110 3$
b110 6$
b110 9$
b110 <$
b11111 &
b11111 *
#125
1$
#126
1%
#130
0$
#135
00
1$
#139
b10 &
b10 *
#140
0$
#145
b1 !
b1 1
1$
#149
0'
#150
0$
#155
b0 !
b0 1
1$
#159
b11 &
b11 *
1'
#160
0$
#165
b1111 !
b1111 1
1$
#169
0'
#170
0$
#175
b1100 !
b1100 1
1$
#179
b1000 &
b1000 *
#180
0$
#185
b10 !
b10 1
1$
#189
b1100 &
b1100 *
#190
0$
#195
b1110 !
b1110 1
1$
#199
b0 &
b0 *
#200
0$
#205
b1100 !
b1100 1
1$
#209
b10000 &
b10000 *
#210
0$
#215
b11 !
b11 1
1$
#219
b100 &
b100 *
1'
#220
0$
#225
1$
#229
0'
#230
0$
#235
b1100 !
b1100 1
1$
#239
b110 &
b110 *
#240
0$
#245
b0 !
b0 1
1$
#249
1'
#250
0$
#255
b110 !
b110 1
1$
#259
b11111 &
b11111 *
#260
0$
#265
b0 !
b0 1
1$
