exam3/3d/a.v
module latch(G,D,Q);
    input G,D;
    output Q;
    reg Q;

    always @ (G or D)
    if(G)
        Q = D;
endmodule

module pe_ffi(CK,D,Q);
    input CK,D;
    output Q;
    //reg  Q;
    wire q1,Q;

    latch l1(!CK,D,q1);
    latch l2(CK,q1,Q);

endmodule

module pe_ffa(CK,D,Q);
    input CK,D;
    output Q;
    reg  Q;

    always @ (posedge CK)
    Q=D;
endmodule



module ff_test;
    reg CK,D;
    wire Qi,Qa;

    pe_ffa ffa (CK,D,Qa);
    pe_ffi ffi (CK,D,Qi);

    initial begin;
        $dumpfile("ff.vcd");    // CKTKWave による波形表示のためのシミュレーション結果出力ファイル名指定
        $dumpvars(0);        // すべての信号を表示対象とするための設定
        $monitor("%4t CK:%b D:%b Qa:%b Qi:%b", $time, CK, D, Qa, Qi);    // 表示設定


        D = 1;
        CK = 0;
        #5 D = 0;
        #10 D = 1;
        #10 D = 0;
        #2 D = 1;
        #8 D = 0;
        #15 $finish;
    end                // シミュレーションの終了指示

    always #10
    begin
        CK <= ~CK;
    end
endmodule

exam3/3d/ff.vcd
$date
	Fri May 29 11:20:20 2020
$end
$version
	Icarus Verilog
$end
$timescale
	1s
$end
$scope module ff_test $end
$var wire 1 ! Qi $end
$var wire 1 " Qa $end
$var reg 1 # CK $end
$var reg 1 $ D $end
$scope module ffa $end
$var wire 1 # CK $end
$var wire 1 $ D $end
$var reg 1 " Q $end
$upscope $end
$scope module ffi $end
$var wire 1 # CK $end
$var wire 1 $ D $end
$var wire 1 % q1 $end
$var wire 1 ! Q $end
$scope module l1 $end
$var wire 1 $ D $end
$var wire 1 & G $end
$var reg 1 % Q $end
$upscope $end
$scope module l2 $end
$var wire 1 % D $end
$var wire 1 # G $end
$var reg 1 ! Q $end
$upscope $end
$upscope $end
$upscope $end
$enddefinitions $end
#0
$dumpvars
1&
1%
1$
0#
x"
x!
$end
#5
0%
0$
#10
0"
0!
0&
1#
#15
1$
#20
1%
1&
0#
#25
0%
0$
#27
1%
1$
#30
1"
1!
0&
1#
#35
0$
#40
0%
1&
0#
#50
0"
0!
0&
1#
