exam6/4b/a.v
`timescale 1 ns / 1 ns

module DFF_AR(CK, D, nCr, Q, nQ);
    input CK, D, nCr;
    output Q, nQ;
    reg Q, nQ;

    always @(posedge CK or negedge nCr)
    begin
        if(~nCr)
            #1 Q = 0;
        else
            #1 Q = D;
        nQ = ~Q;
    end
endmodule

module BCD_COUNT(CK, CE, AR, CO, Q); // CE = 1 で CK = 0 から CK = 1 に立ち上がるとカウントアップ
    input CK, CE, AR;
    output CO;
    reg CO;
    output [3:0] Q;
    reg [3:0] Q;

    always @ (posedge CK or negedge AR)
    begin
        if(~AR | Q[3]&Q[0]&CE)
            Q = 0;
        else if(CE)
            Q = Q+1;

        CO = Q[3]&Q[0]&CE;
    end
endmodule

module main(CK, CE, AR, CO, Q);
    input CK, CE, AR;
    output CO;
    //reg CO;
    output [3:0] Q;
    //reg [3:0] Q;

    wire GCK, nGCK;
    DFF_AR dgl (CK, CE, 1'b1, GCK, nGCK);
    BCD_COUNT bc (GCK&CK, CE, AR, CO, Q);
endmodule

module bcd_test;
    reg CK ,CE, AR;
    wire CO;
    wire [3:0] Qb, Qg;

    BCD_COUNT bc (CK, CE, AR, CO, Qb);
    main m (CK, CE, AR, CO, Qg);

    initial begin
        $dumpfile("test.vcd");
        $dumpvars(0);
        $monitor("%4t CK:%b CE:%b AR:%b CO:%b Qb:%b Qg:%b",$time, CK, CE, AR, CO, Qb, Qg);

        CK = 0;
        CE = 0;
        #15AR = 1;
        #1 AR = 0;
        #4 AR = 1;
           CE = 1;
        #20 CE = 0;
        #20 CE = 1;
        #155 CE = 0;
        #20 CE = 1;
        #39 AR = 0;
        #1 AR = 1;
        #20 $finish;
    end

    always #10
        CK <= ~CK;
endmodule

exam6/4b/test.vcd
$date
	Sun Jun 28 00:29:37 2020
$end
$version
	Icarus Verilog
$end
$timescale
	1ns
$end
$scope module bcd_test $end
$var wire 1 ! CO $end
$var wire 4 " Qg [3:0] $end
$var wire 4 # Qb [3:0] $end
$var reg 1 $ AR $end
$var reg 1 % CE $end
$var reg 1 & CK $end
$scope module bc $end
$var wire 1 $ AR $end
$var wire 1 % CE $end
$var wire 1 & CK $end
$var reg 1 ' CO $end
$var reg 4 ( Q [3:0] $end
$upscope $end
$scope module m $end
$var wire 1 $ AR $end
$var wire 1 % CE $end
$var wire 1 & CK $end
$var wire 1 ! CO $end
$var wire 1 ) nGCK $end
$var wire 4 * Q [3:0] $end
$var wire 1 + GCK $end
$scope module bc $end
$var wire 1 $ AR $end
$var wire 1 % CE $end
$var wire 1 , CK $end
$var reg 1 - CO $end
$var reg 4 . Q [3:0] $end
$upscope $end
$scope module dgl $end
$var wire 1 & CK $end
$var wire 1 % D $end
$var wire 1 / nCr $end
$var reg 1 + Q $end
$var reg 1 ) nQ $end
$upscope $end
$upscope $end
$upscope $end
$enddefinitions $end
#0
$dumpvars
1/
bx .
x-
0,
x+
bx *
x)
bx (
x'
0&
0%
x$
bx #
bx "
x!
$end
#5
0!
0'
b0 #
b0 (
0-
b0 "
b0 *
b0 .
1%
0$
#10
x,
1&
#11
1,
0)
1+
#20
0,
0&
#25
1$
#30
b1 "
b1 *
b1 .
b1 #
b1 (
1,
1&
#40
0,
0&
#50
b10 "
b10 *
b10 .
b10 #
b10 (
1,
1&
#60
0,
0&
#70
b11 "
b11 *
b11 .
b11 #
b11 (
1,
1&
#80
0,
0&
0%
#90
1,
1&
#91
0,
1)
0+
#100
0&
1%
#110
b100 #
b100 (
1&
#111
b100 "
b100 *
b100 .
1,
0)
1+
#120
0,
0&
#130
b101 "
b101 *
b101 .
b101 #
b101 (
1,
1&
#140
0,
0&
#150
b110 "
b110 *
b110 .
b110 #
b110 (
1,
1&
#160
0,
0&
b0 #
b0 (
b0 "
b0 *
b0 .
0$
#170
1,
1&
#180
0,
0&
1$
#190
b1 "
b1 *
b1 .
b1 #
b1 (
1,
1&
#200
0,
0&
0%
#210
1,
1&
#211
0,
1)
0+
#215
1%
#220
0&
#230
b10 #
b10 (
1&
#231
b10 "
b10 *
b10 .
1,
0)
1+
#240
0,
0&
#250
b11 "
b11 *
b11 .
b11 #
b11 (
1,
1&
#260
0,
0&
#270
b100 "
b100 *
b100 .
b100 #
b100 (
1,
1&
#280
0,
0&
#290
b101 "
b101 *
b101 .
b101 #
b101 (
1,
1&
#300
0,
0&
#310
b110 "
b110 *
b110 .
b110 #
b110 (
1,
1&
#320
0,
0&
#330
b111 "
b111 *
b111 .
b111 #
b111 (
1,
1&
