exam3/3b/a.v
module latch(G,D,Q);
    input G,D;
    output Q;
    reg Q;

    always @ (G or D)
    if(G)
        Q = D;
endmodule

module pe_ffi(CK,D,Q);
    input CK,D;
    output Q;
    wire q1;

    latch l1(~CK,D,Q);
    assign q1=Q;
    latch l2(CK,q1,Q);
endmodule

module ff_test;
    reg CK,D;
    wire Q;

    pe_ffi l (CK,D,Q);

    initial begin;
        $dumpfile("ff.vcd");    // CKTKWave による波形表示のためのシミュレーション結果出力ファイル名指定
        $dumpvars(0);        // すべての信号を表示対象とするための設定
        $monitor("%4t CK:%b D:%b Q:%b", $time, CK, D, Q);    // 表示設定

        D = 1;
        CK = 0;
        #5 D = 0;
        #10 D = 1;
        #10 D = 0;
        #2 D = 1;
        #8 D = 0;
        #15 $finish;
    end                // シミュレーションの終了指示

    always #10
    begin
        CK <= ~CK;
    end
endmodule

exam3/3b/ff.vcd
$date
	Sat May 30 23:38:54 2020
$end
$version
	Icarus Verilog
$end
$timescale
	1s
$end
$scope module ff_test $end
$var wire 1 ! Q $end
$var reg 1 " CK $end
$var reg 1 # D $end
$scope module l $end
$var wire 1 " CK $end
$var wire 1 # D $end
$var wire 1 ! Q $end
$var wire 1 $ q1 $end
$scope module l1 $end
$var wire 1 # D $end
$var wire 1 % G $end
$var reg 1 & Q $end
$upscope $end
$scope module l2 $end
$var wire 1 $ D $end
$var wire 1 " G $end
$var reg 1 ' Q $end
$upscope $end
$upscope $end
$upscope $end
$enddefinitions $end
#0
$dumpvars
x'
1&
1%
z$
1#
0"
x!
$end
#5
0&
0#
#10
0%
0!
z'
1"
#15
1#
#20
1!
1&
1%
0"
#25
0!
0&
0#
#27
1!
1&
1#
#30
0%
1"
#35
0#
#40
0!
0&
1%
0"
#50
0%
1"
