exam6/3b/a.v
`timescale 1 ns / 1 ns

module DFF_AR(CK, D, nCr, Q, nQ);
    input CK, D, nCr;
    output Q, nQ;
    reg Q, nQ;

    always @(posedge CK or negedge nCr)
    begin
        if(~nCr)
            #1 Q = 0;
        else
            #1 Q = D;
        nQ = ~Q;
    end
endmodule

module BCD_CNT_A(CK, nClear, Q); // CK：クロック入力，nClear：負論理リセット入力，Q：カウント出力
    input CK,nClear;
    output [3:0] Q;

    wire q1, q2, q3, q4, nq1, nq2, nq3, nq4;
    wire clear;

    assign clear = !(q2&q4)&nClear;

    DFF_AR l1(CK , nq1, clear, q1, nq1);
    DFF_AR l2(nq1, nq2, clear, q2, nq2);
    DFF_AR l3(nq2, nq3, clear, q3, nq3);
    DFF_AR l4(nq3, nq4, clear, q4, nq4);

    assign Q = {q4,q3,q2,q1};
endmodule


module BCD_TEST;
    reg CK, nClear;
    wire [3:0] Q;

    BCD_CNT_A dx (CK, nClear, Q);

    initial begin
        $dumpfile("test.vcd");
        $dumpvars(0);
        $monitor("%4t CK:%b nClear:%b Q:%b",$time, CK, nClear, Q);

        CK = 0;
        nClear = 1;
        #9 nClear = 0;
        #1 nClear = 1;

        #25 nClear = 0;
        #5 nClear = 1;
        #250 $finish;
    end

    always #10
        CK <= ~CK;
endmodule

exam6/3b/test.vcd
$date
	Sat Jun 27 23:30:36 2020
$end
$version
	Icarus Verilog
$end
$timescale
	1ns
$end
$scope module BCD_TEST $end
$var wire 4 ! Q [3:0] $end
$var reg 1 " CK $end
$var reg 1 # nClear $end
$scope module dx $end
$var wire 1 " CK $end
$var wire 1 $ clear $end
$var wire 1 # nClear $end
$var wire 1 % q4 $end
$var wire 1 & q3 $end
$var wire 1 ' q2 $end
$var wire 1 ( q1 $end
$var wire 1 ) nq4 $end
$var wire 1 * nq3 $end
$var wire 1 + nq2 $end
$var wire 1 , nq1 $end
$var wire 4 - Q [3:0] $end
$scope module l1 $end
$var wire 1 " CK $end
$var wire 1 $ nCr $end
$var wire 1 , D $end
$var reg 1 ( Q $end
$var reg 1 , nQ $end
$upscope $end
$scope module l2 $end
$var wire 1 , CK $end
$var wire 1 $ nCr $end
$var wire 1 + D $end
$var reg 1 ' Q $end
$var reg 1 + nQ $end
$upscope $end
$scope module l3 $end
$var wire 1 + CK $end
$var wire 1 $ nCr $end
$var wire 1 * D $end
$var reg 1 & Q $end
$var reg 1 * nQ $end
$upscope $end
$scope module l4 $end
$var wire 1 * CK $end
$var wire 1 $ nCr $end
$var wire 1 ) D $end
$var reg 1 % Q $end
$var reg 1 ) nQ $end
$upscope $end
$upscope $end
$upscope $end
$enddefinitions $end
#0
$dumpvars
bx -
x,
x+
x*
x)
x(
x'
x&
x%
x$
1#
0"
bx !
$end
#9
0$
0#
#10
1"
1$
1,
0(
1+
0'
1*
0&
1)
b0 !
b0 -
0%
1#
#11
0$
0,
1(
0+
1'
0*
1&
0)
b1111 !
b1111 -
1%
#12
1$
1,
0(
1+
0'
1*
0&
1)
b0 !
b0 -
0%
#20
0"
#30
1"
#31
0,
b1 !
b1 -
1(
#35
0$
0#
#36
1,
b0 !
b0 -
0(
#40
0"
1$
1#
#50
1"
#51
0,
b1 !
b1 -
1(
#60
0"
#70
1"
#71
1,
b0 !
b0 -
0(
#72
0+
b10 !
b10 -
1'
#80
0"
#90
1"
#91
0,
b11 !
b11 -
1(
#100
0"
#110
1"
#111
1,
b10 !
b10 -
0(
#112
1+
b0 !
b0 -
0'
#113
0*
b100 !
b100 -
1&
#120
0"
#130
1"
#131
0,
b101 !
b101 -
1(
#140
0"
#150
1"
#151
1,
b100 !
b100 -
0(
#152
0+
b110 !
b110 -
1'
#160
0"
#170
1"
#171
0,
b111 !
b111 -
1(
#180
0"
#190
1"
#191
1,
b110 !
b110 -
0(
#192
1+
b100 !
b100 -
0'
#193
1*
b0 !
b0 -
0&
#194
0)
b1000 !
b1000 -
1%
#200
0"
#210
1"
#211
0,
b1001 !
b1001 -
1(
#220
0"
#230
1"
#231
1,
b1000 !
b1000 -
0(
#232
0$
0+
b1010 !
b1010 -
1'
#233
1$
1+
0'
1)
b0 !
b0 -
0%
#240
0"
#250
1"
#251
0,
b1 !
b1 -
1(
#260
0"
#270
1"
#271
1,
b0 !
b0 -
0(
#272
0+
b10 !
b10 -
1'
